{
  "14.jpg": {
    "filename": "14.jpg",
    "format": "JPEG",
    "size": [
      2526,
      1894
    ],
    "width": 2526,
    "height": 1894,
    "exif": {
      "GPSInfo": "{0: b'\\x02\\x02\\x00\\x00', 1: 'N', 2: (12.0, 57.867, 0.0), 3: 'E', 4: (77.0, 34.61748, 0.0)}",
      "ResolutionUnit": 2.0,
      "ExifOffset": 436.0,
      "ImageDescription": "Early morning (7am ~ 8am) crowds at Krishna Rajendra wholesale flower market (aka KR Market) in Bangalore. From here, fresh flowers go to temples, weddings, hotels and florists across the city.",
      "Make": "FUJIFILM",
      "Model": "GFX 50S",
      "Software": "Adobe Photoshop Lightroom Classic 15.0.1 (Macintosh)",
      "DateTime": "2025:11:29 17:25:56",
      "XResolution": 240.0,
      "YResolution": 240.0,
      "ExifVersion": "b'0231'",
      "ShutterSpeedValue": 7.965784,
      "ApertureValue": 6.0,
      "DateTimeOriginal": "2023:04:01 07:57:20",
      "DateTimeDigitized": "2023:04:01 07:57:20",
      "BrightnessValue": 7.62,
      "ExposureBiasValue": 0.0,
      "MaxApertureValue": 4.0,
      "MeteringMode": 5.0,
      "LightSource": 0.0,
      "Flash": 1.0,
      "FocalLength": 47.9,
      "ColorSpace": 1.0,
      "FocalLengthIn35mmFilm": 38.0,
      "FocalPlaneXResolution": 1876.3636474609375,
      "FocalPlaneYResolution": 1876.3636474609375,
      "OffsetTime": "+05:30",
      "FocalPlaneResolutionUnit": 3.0,
      "Sharpness": 0.0,
      "SubjectDistanceRange": 0.0,
      "SensingMethod": 2.0,
      "FileSource": "b'\\x03'",
      "ExposureTime": 0.004,
      "FNumber": 8.0,
      "SceneType": "b'\\x01'",
      "ExposureProgram": 1.0,
      "CustomRendered": 0.0,
      "ISOSpeedRatings": 400.0,
      "ExposureMode": 1.0,
      "SensitivityType": 1.0,
      "StandardOutputSensitivity": 400.0,
      "WhiteBalance": 0.0,
      "BodySerialNumber": "71001298",
      "LensSpecification": "(45.0, 100.0, 4.0, 4.0)",
      "LensMake": "FUJIFILM",
      "LensModel": "GF45-100mmF4 R LM OIS WR",
      "LensSerialNumber": "05A00486",
      "SceneCaptureType": 0.0
    },
    "photography": {
      "camera_make": "FUJIFILM",
      "camera_model": "GFX 50S",
      "lens_model": "GF45-100mmF4 R LM OIS WR",
      "aperture": "f/8.0",
      "shutter_speed": "1/250s",
      "iso": 400.0,
      "focal_length": "48mm",
      "date_original": "2023:04:01 07:57:20",
      "description": "Early morning (7am ~ 8am) crowds at Krishna Rajendra wholesale flower market (aka KR Market) in Bangalore. From here, fresh flowers go to temples, weddings, hotels and florists across the city."
    }
  },
  "15.jpg": {
    "filename": "15.jpg",
    "format": "JPEG",
    "size": [
      2497,
      1873
    ],
    "width": 2497,
    "height": 1873,
    "exif": {
      "GPSInfo": "{0: b'\\x02\\x02\\x00\\x00', 1: 'N', 2: (12.0, 58.45896, 0.0), 3: 'E', 4: (77.0, 36.45984, 0.0)}",
      "ResolutionUnit": 2.0,
      "ExifOffset": 308.0,
      "ImageDescription": "Bangalore city centre - Church Street - restaurants and shopping",
      "Make": "FUJIFILM",
      "Model": "GFX 50S",
      "Software": "Adobe Photoshop Lightroom Classic 15.0.1 (Macintosh)",
      "DateTime": "2025:11:29 17:25:55",
      "XResolution": 240.0,
      "YResolution": 240.0,
      "ExifVersion": "b'0231'",
      "ShutterSpeedValue": 7.714246,
      "ApertureValue": 4.0,
      "DateTimeOriginal": "2022:11:12 17:13:00",
      "DateTimeDigitized": "2022:11:12 17:13:00",
      "BrightnessValue": 2.35,
      "ExposureBiasValue": -0.67,
      "MaxApertureValue": 4.0,
      "MeteringMode": 5.0,
      "LightSource": 0.0,
      "Flash": 0.0,
      "FocalLength": 45.0,
      "ColorSpace": 1.0,
      "FocalLengthIn35mmFilm": 36.0,
      "FocalPlaneXResolution": 1876.3636474609375,
      "FocalPlaneYResolution": 1876.3636474609375,
      "OffsetTime": "+05:30",
      "FocalPlaneResolutionUnit": 3.0,
      "Sharpness": 0.0,
      "SubjectDistanceRange": 0.0,
      "SensingMethod": 2.0,
      "FileSource": "b'\\x03'",
      "ExposureTime": 0.004761904761904762,
      "FNumber": 4.0,
      "SceneType": "b'\\x01'",
      "ExposureProgram": 3.0,
      "CustomRendered": 0.0,
      "ISOSpeedRatings": 1600.0,
      "ExposureMode": 0.0,
      "SensitivityType": 1.0,
      "StandardOutputSensitivity": 1600.0,
      "WhiteBalance": 0.0,
      "BodySerialNumber": "71001298",
      "LensSpecification": "(45.0, 100.0, 4.0, 4.0)",
      "LensMake": "FUJIFILM",
      "LensModel": "GF45-100mmF4 R LM OIS WR",
      "LensSerialNumber": "05A00486",
      "SceneCaptureType": 0.0
    },
    "photography": {
      "camera_make": "FUJIFILM",
      "camera_model": "GFX 50S",
      "lens_model": "GF45-100mmF4 R LM OIS WR",
      "aperture": "f/4.0",
      "shutter_speed": "1/209s",
      "iso": 1600.0,
      "focal_length": "45mm",
      "date_original": "2022:11:12 17:13:00",
      "description": "Bangalore city centre - Church Street - restaurants and shopping"
    }
  },
  "01.jpg": {
    "filename": "01.jpg",
    "format": "JPEG",
    "size": [
      2271,
      1703
    ],
    "width": 2271,
    "height": 1703,
    "exif": {
      "ResolutionUnit": 2.0,
      "ExifOffset": 476.0,
      "ImageDescription": "Mumbai cityscape and skyline. Mahalakshmi racecourse and station in the foreground. The Imperial twin towers (by Hafeez Contractor) in the background.",
      "Make": "NIKON CORPORATION",
      "Model": "NIKON D3S",
      "Software": "Adobe Photoshop Lightroom Classic 15.0.1 (Macintosh)",
      "DateTime": "2025:11:29 17:25:53",
      "Artist": "Mahesh Shantaram / ms@thecontrarian.in",
      "Copyright": "© Mahesh Shantaram",
      "XResolution": 240.0,
      "YResolution": 240.0,
      "ExifVersion": "b'0231'",
      "ShutterSpeedValue": 6.965784,
      "ApertureValue": 6.0,
      "DateTimeOriginal": "2014:06:06 18:44:30",
      "DateTimeDigitized": "2014:06:06 18:44:30",
      "ExposureBiasValue": 0.0,
      "MaxApertureValue": 3.0,
      "MeteringMode": 2.0,
      "LightSource": 0.0,
      "Flash": 0.0,
      "FocalLength": 70.0,
      "ColorSpace": 1.0,
      "WhiteBalance": 0.0,
      "DigitalZoomRatio": 1.0,
      "FocalLengthIn35mmFilm": 70.0,
      "SceneCaptureType": 0.0,
      "OffsetTime": "+05:30",
      "Contrast": 0.0,
      "SubsecTimeDigitized": "49",
      "Sharpness": 0.0,
      "SubjectDistanceRange": 0.0,
      "SensingMethod": 2.0,
      "FileSource": "b'\\x03'",
      "ExposureTime": 0.008,
      "FNumber": 8.0,
      "SceneType": "b'\\x01'",
      "ExposureProgram": 3.0,
      "CFAPattern": "b'\\x02\\x00\\x02\\x00\\x00\\x01\\x01\\x02'",
      "CustomRendered": 0.0,
      "ISOSpeedRatings": 400.0,
      "ExposureMode": 0.0,
      "BodySerialNumber": "2024568",
      "LensSpecification": "(24.0, 70.0, 2.8, 2.8)",
      "LensModel": "24.0-70.0 mm f/2.8",
      "GainControl": 1.0,
      "Saturation": 0.0
    },
    "photography": {
      "camera_make": "NIKON CORPORATION",
      "camera_model": "D3S",
      "lens_model": "24.0-70.0 mm f/2.8",
      "aperture": "f/8.0",
      "shutter_speed": "1/125s",
      "iso": 400.0,
      "focal_length": "70mm",
      "date_original": "2014:06:06 18:44:30",
      "artist": "Mahesh Shantaram / ms@thecontrarian.in",
      "copyright": "© Mahesh Shantaram",
      "description": "Mumbai cityscape and skyline. Mahalakshmi racecourse and station in the foreground. The Imperial twin towers (by Hafeez Contractor) in the background.",
      "title": "Mumbai cityscape and skyline"
    }
  },
  "17.jpg": {
    "filename": "17.jpg",
    "format": "JPEG",
    "size": [
      2264,
      1698
    ],
    "width": 2264,
    "height": 1698,
    "exif": {
      "ResolutionUnit": 2.0,
      "ExifOffset": 378.0,
      "ImageDescription": "Sumant Sinha, an Indian renewable energy entrepreneur, is the founding chairman and managing director of ReNew Power.",
      "Make": "FUJIFILM",
      "Model": "GFX 50S",
      "Software": "Adobe Photoshop Lightroom Classic 15.0.1 (Macintosh)",
      "DateTime": "2025:11:29 17:25:55",
      "Copyright": "MAHESH SHANTARAM",
      "XResolution": 240.0,
      "YResolution": 240.0,
      "ExifVersion": "b'0231'",
      "ShutterSpeedValue": 7.321928,
      "ApertureValue": 4.0,
      "DateTimeOriginal": "2020:08:08 17:54:27",
      "DateTimeDigitized": "2020:08:08 17:54:27",
      "BrightnessValue": 6.36,
      "ExposureBiasValue": 0.0,
      "MaxApertureValue": 4.0,
      "MeteringMode": 5.0,
      "LightSource": 0.0,
      "Flash": 1.0,
      "FocalLength": 58.6,
      "ColorSpace": 1.0,
      "FocalLengthIn35mmFilm": 46.0,
      "FocalPlaneXResolution": 1876.3636474609375,
      "FocalPlaneYResolution": 1876.3636474609375,
      "OffsetTime": "+05:30",
      "FocalPlaneResolutionUnit": 3.0,
      "Sharpness": 0.0,
      "SubjectDistanceRange": 0.0,
      "SensingMethod": 2.0,
      "FileSource": "b'\\x03'",
      "ExposureTime": 0.00625,
      "FNumber": 4.0,
      "SceneType": "b'\\x01'",
      "ExposureProgram": 3.0,
      "CustomRendered": 0.0,
      "ISOSpeedRatings": 100.0,
      "ExposureMode": 0.0,
      "SensitivityType": 1.0,
      "StandardOutputSensitivity": 100.0,
      "WhiteBalance": 0.0,
      "BodySerialNumber": "71001298",
      "LensSpecification": "(45.0, 100.0, 4.0, 4.0)",
      "LensMake": "FUJIFILM",
      "LensModel": "GF45-100mmF4 R LM OIS WR",
      "LensSerialNumber": "05A00486",
      "SceneCaptureType": 0.0
    },
    "photography": {
      "camera_make": "FUJIFILM",
      "camera_model": "GFX 50S",
      "lens_model": "GF45-100mmF4 R LM OIS WR",
      "aperture": "f/4.0",
      "shutter_speed": "1/160s",
      "iso": 100.0,
      "focal_length": "59mm",
      "date_original": "2020:08:08 17:54:27",
      "copyright": "MAHESH SHANTARAM",
      "description": "Sumant Sinha, an Indian renewable energy entrepreneur, is the founding chairman and managing director of ReNew Power."
    }
  },
  "03.jpg": {
    "filename": "03.jpg",
    "format": "JPEG",
    "size": [
      2154,
      1616
    ],
    "width": 2154,
    "height": 1616,
    "exif": {
      "ResolutionUnit": 2.0,
      "ExifOffset": 364.0,
      "ImageDescription": "Bhaskar Gowda, proprietor of Himalaya Water Supply, at his filling station in Pattandur Agrahara in Whitefield, Bangalore.",
      "Make": "NIKON CORPORATION",
      "Model": "NIKON D4S",
      "Software": "Adobe Photoshop Lightroom Classic 15.0.1 (Macintosh)",
      "DateTime": "2025:11:29 17:25:53",
      "XResolution": 240.0,
      "YResolution": 240.0,
      "ExifVersion": "b'0231'",
      "ShutterSpeedValue": 9.550747,
      "ApertureValue": 6.0,
      "DateTimeOriginal": "2017:01:20 16:43:34",
      "DateTimeDigitized": "2017:01:20 16:43:34",
      "ExposureBiasValue": 0.0,
      "MaxApertureValue": 3.0,
      "MeteringMode": 5.0,
      "LightSource": 0.0,
      "Flash": 13.0,
      "FocalLength": 35.0,
      "ColorSpace": 1.0,
      "WhiteBalance": 0.0,
      "DigitalZoomRatio": 1.0,
      "FocalPlaneXResolution": 1368.8888854980469,
      "FocalPlaneYResolution": 1368.8888854980469,
      "OffsetTime": "+05:30",
      "FocalPlaneResolutionUnit": 3.0,
      "SubsecTimeDigitized": "69",
      "Sharpness": 0.0,
      "SubjectDistanceRange": 0.0,
      "SensingMethod": 2.0,
      "FileSource": "b'\\x03'",
      "ExposureTime": 0.0013333333333333333,
      "FNumber": 8.0,
      "SceneType": "b'\\x01'",
      "ExposureProgram": 1.0,
      "CFAPattern": "b'\\x02\\x00\\x02\\x00\\x00\\x01\\x01\\x02'",
      "CustomRendered": 0.0,
      "ISOSpeedRatings": 400.0,
      "ExposureMode": 1.0,
      "SensitivityType": 2.0,
      "BodySerialNumber": "2014595",
      "LensSpecification": "(24.0, 70.0, 2.8, 2.8)",
      "LensModel": "24.0-70.0 mm f/2.8",
      "FocalLengthIn35mmFilm": 35.0,
      "SceneCaptureType": 0.0,
      "GainControl": 1.0,
      "Contrast": 0.0,
      "Saturation": 0.0
    },
    "photography": {
      "camera_make": "NIKON CORPORATION",
      "camera_model": "D4S",
      "lens_model": "24.0-70.0 mm f/2.8",
      "aperture": "f/8.0",
      "shutter_speed": "1/750s",
      "iso": 400.0,
      "focal_length": "35mm",
      "date_original": "2017:01:20 16:43:34",
      "description": "Bhaskar Gowda, proprietor of Himalaya Water Supply, at his filling station in Pattandur Agrahara in Whitefield, Bangalore."
    }
  },
  "02.jpg": {
    "filename": "02.jpg",
    "format": "JPEG",
    "size": [
      2271,
      1703
    ],
    "width": 2271,
    "height": 1703,
    "exif": {
      "ResolutionUnit": 2.0,
      "ExifOffset": 480.0,
      "ImageDescription": "Successful and controvertial commerical architect Hafeez Contractor at one of his under-development properties in Mumbai. For the New York Times Magazine.",
      "Make": "NIKON CORPORATION",
      "Model": "NIKON D3S",
      "Software": "Adobe Photoshop Lightroom Classic 15.0.1 (Macintosh)",
      "DateTime": "2025:11:29 17:25:53",
      "Artist": "Mahesh Shantaram / ms@thecontrarian.in",
      "Copyright": "© Mahesh Shantaram",
      "XResolution": 240.0,
      "YResolution": 240.0,
      "ExifVersion": "b'0231'",
      "ShutterSpeedValue": 5.906891,
      "ApertureValue": 8.0,
      "DateTimeOriginal": "2014:06:07 19:03:59",
      "DateTimeDigitized": "2014:06:07 19:03:59",
      "ExposureBiasValue": 0.0,
      "MaxApertureValue": 3.0,
      "MeteringMode": 2.0,
      "LightSource": 0.0,
      "Flash": 13.0,
      "FocalLength": 50.0,
      "ColorSpace": 1.0,
      "WhiteBalance": 0.0,
      "DigitalZoomRatio": 1.0,
      "FocalLengthIn35mmFilm": 50.0,
      "SceneCaptureType": 0.0,
      "OffsetTime": "+05:30",
      "Contrast": 0.0,
      "SubsecTimeDigitized": "21",
      "Sharpness": 0.0,
      "SubjectDistanceRange": 0.0,
      "SensingMethod": 2.0,
      "FileSource": "b'\\x03'",
      "ExposureTime": 0.016666666666666666,
      "FNumber": 16.0,
      "SceneType": "b'\\x01'",
      "ExposureProgram": 1.0,
      "CFAPattern": "b'\\x02\\x00\\x02\\x00\\x00\\x01\\x01\\x02'",
      "CustomRendered": 0.0,
      "ISOSpeedRatings": 1600.0,
      "ExposureMode": 1.0,
      "BodySerialNumber": "2024568",
      "LensSpecification": "(24.0, 70.0, 2.8, 2.8)",
      "LensModel": "24.0-70.0 mm f/2.8",
      "GainControl": 2.0,
      "Saturation": 0.0
    },
    "photography": {
      "camera_make": "NIKON CORPORATION",
      "camera_model": "D3S",
      "lens_model": "24.0-70.0 mm f/2.8",
      "aperture": "f/16.0",
      "shutter_speed": "1/60s",
      "iso": 1600.0,
      "focal_length": "50mm",
      "date_original": "2014:06:07 19:03:59",
      "artist": "Mahesh Shantaram / ms@thecontrarian.in",
      "copyright": "© Mahesh Shantaram",
      "description": "Successful and controvertial commerical architect Hafeez Contractor at one of his under-development properties in Mumbai. For the New York Times Magazine."
    }
  },
  "16.jpg": {
    "filename": "16.jpg",
    "format": "JPEG",
    "size": [
      2560,
      1920
    ],
    "width": 2560,
    "height": 1920,
    "exif": {
      "ResolutionUnit": 2.0,
      "ExifOffset": 796.0,
      "ImageDescription": "The headquarters of ReNew Power is located in Gurugram city (formerly Gurgaon) in the National Capital Region surrounding Delhi. The effects of Coronavirus-induced lockdown is still felt and seen. Delhi Metro's iconic Yellow Line services remain suspended since March 22nd. And the air quality is better than Delhiites have ever known it to be. Less than a year ago, the alarming levels of pollution in the capital forced the Supreme Court to reprimand the local government for inaction. Seen here: Aravali Biodiversity Park, Gurugram.",
      "Make": "FUJIFILM",
      "Model": "GFX 50S",
      "Software": "Adobe Photoshop Lightroom Classic 15.0.1 (Macintosh)",
      "DateTime": "2025:11:29 17:25:55",
      "Copyright": "MAHESH SHANTARAM",
      "XResolution": 240.0,
      "YResolution": 240.0,
      "ExifVersion": "b'0231'",
      "ShutterSpeedValue": 6.714246,
      "ApertureValue": 6.0,
      "DateTimeOriginal": "2020:08:07 14:43:20",
      "DateTimeDigitized": "2020:08:07 14:43:20",
      "BrightnessValue": 7.72,
      "ExposureBiasValue": 0.0,
      "MaxApertureValue": 4.0,
      "MeteringMode": 5.0,
      "LightSource": 0.0,
      "Flash": 0.0,
      "FocalLength": 100.0,
      "ColorSpace": 1.0,
      "FocalLengthIn35mmFilm": 79.0,
      "FocalPlaneXResolution": 1876.3636474609375,
      "FocalPlaneYResolution": 1876.3636474609375,
      "OffsetTime": "+05:30",
      "FocalPlaneResolutionUnit": 3.0,
      "Sharpness": 0.0,
      "SubjectDistanceRange": 0.0,
      "SensingMethod": 2.0,
      "FileSource": "b'\\x03'",
      "ExposureTime": 0.009523809523809525,
      "FNumber": 8.0,
      "SceneType": "b'\\x01'",
      "ExposureProgram": 3.0,
      "CustomRendered": 0.0,
      "ISOSpeedRatings": 100.0,
      "ExposureMode": 0.0,
      "SensitivityType": 1.0,
      "StandardOutputSensitivity": 100.0,
      "WhiteBalance": 0.0,
      "BodySerialNumber": "71001298",
      "LensSpecification": "(45.0, 100.0, 4.0, 4.0)",
      "LensMake": "FUJIFILM",
      "LensModel": "GF45-100mmF4 R LM OIS WR",
      "LensSerialNumber": "05A00486",
      "SceneCaptureType": 0.0
    },
    "photography": {
      "camera_make": "FUJIFILM",
      "camera_model": "GFX 50S",
      "lens_model": "GF45-100mmF4 R LM OIS WR",
      "aperture": "f/8.0",
      "shutter_speed": "1/104s",
      "iso": 100.0,
      "focal_length": "100mm",
      "date_original": "2020:08:07 14:43:20",
      "copyright": "MAHESH SHANTARAM",
      "description": "The headquarters of ReNew Power is located in Gurugram city (formerly Gurgaon) in the National Capital Region surrounding Delhi. The effects of Coronavirus-induced lockdown is still felt and seen. Delhi Metro's iconic Yellow Line services remain suspended since March 22nd. And the air quality is better than Delhiites have ever known it to be. Less than a year ago, the alarming levels of pollution in the capital forced the Supreme Court to reprimand the local government for inaction. Seen here: Aravali Biodiversity Park, Gurugram."
    }
  },
  "12.jpg": {
    "filename": "12.jpg",
    "format": "JPEG",
    "size": [
      2329,
      1747
    ],
    "width": 2329,
    "height": 1747,
    "exif": {
      "GPSInfo": "{0: b'\\x02\\x02\\x00\\x00', 1: 'N', 2: (12.0, 57.41568, 0.0), 3: 'E', 4: (77.0, 42.10062, 0.0)}",
      "ResolutionUnit": 2.0,
      "ExifOffset": 348.0,
      "ImageDescription": "Grid locked traffic, like the one seen here at Maratthahalli junction, is a familiar scene in Bangalore.",
      "Make": "FUJIFILM",
      "Model": "GFX 50S",
      "Software": "Adobe Photoshop Lightroom Classic 15.0.1 (Macintosh)",
      "DateTime": "2025:11:29 17:25:55",
      "XResolution": 240.0,
      "YResolution": 240.0,
      "ExifVersion": "b'0231'",
      "ShutterSpeedValue": 6.965784,
      "ApertureValue": 4.0,
      "DateTimeOriginal": "2022:11:16 18:06:01",
      "DateTimeDigitized": "2022:11:16 18:06:01",
      "BrightnessValue": 2.15,
      "ExposureBiasValue": 0.0,
      "MaxApertureValue": 4.0,
      "MeteringMode": 5.0,
      "LightSource": 0.0,
      "Flash": 0.0,
      "FocalLength": 69.0,
      "ColorSpace": 1.0,
      "FocalLengthIn35mmFilm": 55.0,
      "FocalPlaneXResolution": 1876.3636474609375,
      "FocalPlaneYResolution": 1876.3636474609375,
      "OffsetTime": "+05:30",
      "FocalPlaneResolutionUnit": 3.0,
      "Sharpness": 0.0,
      "SubjectDistanceRange": 0.0,
      "SensingMethod": 2.0,
      "FileSource": "b'\\x03'",
      "ExposureTime": 0.008,
      "FNumber": 4.0,
      "SceneType": "b'\\x01'",
      "ExposureProgram": 1.0,
      "CustomRendered": 0.0,
      "ISOSpeedRatings": 3200.0,
      "ExposureMode": 1.0,
      "SensitivityType": 1.0,
      "StandardOutputSensitivity": 3200.0,
      "WhiteBalance": 0.0,
      "BodySerialNumber": "71001298",
      "LensSpecification": "(45.0, 100.0, 4.0, 4.0)",
      "LensMake": "FUJIFILM",
      "LensModel": "GF45-100mmF4 R LM OIS WR",
      "LensSerialNumber": "05A00486",
      "SceneCaptureType": 0.0
    },
    "photography": {
      "camera_make": "FUJIFILM",
      "camera_model": "GFX 50S",
      "lens_model": "GF45-100mmF4 R LM OIS WR",
      "aperture": "f/4.0",
      "shutter_speed": "1/125s",
      "iso": 3200.0,
      "focal_length": "69mm",
      "date_original": "2022:11:16 18:06:01",
      "description": "Grid locked traffic, like the one seen here at Maratthahalli junction, is a familiar scene in Bangalore."
    }
  },
  "06.jpg": {
    "filename": "06.jpg",
    "format": "JPEG",
    "size": [
      2276,
      1707
    ],
    "width": 2276,
    "height": 1707,
    "exif": {
      "ResolutionUnit": 2.0,
      "ExifOffset": 324.0,
      "ImageDescription": "Nawab Shafath Ali Khan, India's last true \"white hunter\" at his home in Hyderabad, India.",
      "Make": "FUJIFILM",
      "Model": "X-T2",
      "Software": "Adobe Photoshop Lightroom Classic 15.0.1 (Macintosh)",
      "DateTime": "2025:11:29 17:25:53",
      "XResolution": 240.0,
      "YResolution": 240.0,
      "ExifVersion": "b'0231'",
      "ShutterSpeedValue": 6.965784,
      "ApertureValue": 4.0,
      "DateTimeOriginal": "2019:01:15 13:51:18",
      "DateTimeDigitized": "2019:01:15 13:51:18",
      "BrightnessValue": 1.47,
      "ExposureBiasValue": 0.0,
      "MaxApertureValue": 3.0,
      "MeteringMode": 5.0,
      "LightSource": 0.0,
      "Flash": 1.0,
      "FocalLength": 22.0,
      "ColorSpace": 1.0,
      "FocalLengthIn35mmFilm": 33.0,
      "FocalPlaneXResolution": 2553.214599609375,
      "FocalPlaneYResolution": 2553.214599609375,
      "OffsetTime": "+05:30",
      "FocalPlaneResolutionUnit": 3.0,
      "Sharpness": 0.0,
      "SubjectDistanceRange": 0.0,
      "SensingMethod": 2.0,
      "FileSource": "b'\\x03'",
      "ExposureTime": 0.008,
      "FNumber": 4.0,
      "SceneType": "b'\\x01'",
      "ExposureProgram": 1.0,
      "CustomRendered": 0.0,
      "ISOSpeedRatings": 400.0,
      "ExposureMode": 1.0,
      "SensitivityType": 1.0,
      "WhiteBalance": 0.0,
      "BodySerialNumber": "73M53215",
      "LensSpecification": "(16.0, 55.0, 2.8, 2.8)",
      "LensMake": "FUJIFILM",
      "LensModel": "XF16-55mmF2.8 R LM WR",
      "LensSerialNumber": "76B30305",
      "SceneCaptureType": 0.0
    },
    "photography": {
      "camera_make": "FUJIFILM",
      "camera_model": "X-T2",
      "lens_model": "XF16-55mmF2.8 R LM WR",
      "aperture": "f/4.0",
      "shutter_speed": "1/125s",
      "iso": 400.0,
      "focal_length": "22mm",
      "date_original": "2019:01:15 13:51:18",
      "description": "Nawab Shafath Ali Khan, India's last true \"white hunter\" at his home in Hyderabad, India."
    }
  },
  "07.jpg": {
    "filename": "07.jpg",
    "format": "JPEG",
    "size": [
      2276,
      1707
    ],
    "width": 2276,
    "height": 1707,
    "exif": {
      "ResolutionUnit": 2.0,
      "ExifOffset": 326.0,
      "ImageDescription": "Bhushan Kumar arrives at Mumbai's Filmcity,  making an entry in a cherry-red Rolls-Royce Phantom.",
      "Make": "FUJIFILM",
      "Model": "X-T2",
      "Software": "Adobe Photoshop Lightroom Classic 15.0.1 (Macintosh)",
      "DateTime": "2025:11:29 17:25:54",
      "XResolution": 240.0,
      "YResolution": 240.0,
      "ExifVersion": "b'0231'",
      "ShutterSpeedValue": 5.78136,
      "ApertureValue": 2.970854,
      "DateTimeOriginal": "2019:09:25 20:04:33",
      "DateTimeDigitized": "2019:09:25 20:04:33",
      "BrightnessValue": -2.43,
      "ExposureBiasValue": -1.0,
      "MaxApertureValue": 3.0,
      "MeteringMode": 5.0,
      "LightSource": 0.0,
      "Flash": 1.0,
      "FocalLength": 20.6,
      "ColorSpace": 1.0,
      "FocalLengthIn35mmFilm": 31.0,
      "FocalPlaneXResolution": 2553.214599609375,
      "FocalPlaneYResolution": 2553.214599609375,
      "OffsetTime": "+05:30",
      "FocalPlaneResolutionUnit": 3.0,
      "Sharpness": 0.0,
      "SubjectDistanceRange": 0.0,
      "SensingMethod": 2.0,
      "FileSource": "b'\\x03'",
      "ExposureTime": 0.01818181818181818,
      "FNumber": 2.8,
      "SceneType": "b'\\x01'",
      "ExposureProgram": 3.0,
      "CustomRendered": 0.0,
      "ISOSpeedRatings": 3200.0,
      "ExposureMode": 0.0,
      "SensitivityType": 1.0,
      "WhiteBalance": 0.0,
      "BodySerialNumber": "73M53215",
      "LensSpecification": "(16.0, 55.0, 2.8, 2.8)",
      "LensMake": "FUJIFILM",
      "LensModel": "XF16-55mmF2.8 R LM WR",
      "LensSerialNumber": "76B30305",
      "SceneCaptureType": 0.0
    },
    "photography": {
      "camera_make": "FUJIFILM",
      "camera_model": "X-T2",
      "lens_model": "XF16-55mmF2.8 R LM WR",
      "aperture": "f/2.8",
      "shutter_speed": "1/55s",
      "iso": 3200.0,
      "focal_length": "21mm",
      "date_original": "2019:09:25 20:04:33",
      "description": "Bhushan Kumar arrives at Mumbai's Filmcity,  making an entry in a cherry-red Rolls-Royce Phantom."
    }
  },
  "13.jpg": {
    "filename": "13.jpg",
    "format": "JPEG",
    "size": [
      2560,
      1920
    ],
    "width": 2560,
    "height": 1920,
    "exif": {
      "GPSInfo": "{0: b'\\x02\\x02\\x00\\x00', 1: 'N', 2: (12.0, 58.18638, 0.0), 3: 'E', 4: (77.0, 34.54422, 0.0)}",
      "ResolutionUnit": 2.0,
      "ExifOffset": 414.0,
      "ImageDescription": "Shoppers at Bangalore's Chikpet area on a Sunday. The modern shopping malls can only look on with envy at footfalls that traditional shopping districts like Chikpet enjoy.",
      "Make": "FUJIFILM",
      "Model": "GFX 50S",
      "Software": "Adobe Photoshop Lightroom Classic 15.0.1 (Macintosh)",
      "DateTime": "2025:11:29 17:25:55",
      "XResolution": 240.0,
      "YResolution": 240.0,
      "ExifVersion": "b'0231'",
      "ShutterSpeedValue": 9.965784,
      "ApertureValue": 6.0,
      "DateTimeOriginal": "2023:04:02 14:17:37",
      "DateTimeDigitized": "2023:04:02 14:17:37",
      "BrightnessValue": 8.75,
      "ExposureBiasValue": 0.0,
      "MaxApertureValue": 4.0,
      "MeteringMode": 5.0,
      "LightSource": 0.0,
      "Flash": 1.0,
      "FocalLength": 100.0,
      "ColorSpace": 1.0,
      "FocalLengthIn35mmFilm": 79.0,
      "FocalPlaneXResolution": 1876.3636474609375,
      "FocalPlaneYResolution": 1876.3636474609375,
      "OffsetTime": "+05:30",
      "FocalPlaneResolutionUnit": 3.0,
      "Sharpness": 0.0,
      "SubjectDistanceRange": 0.0,
      "SensingMethod": 2.0,
      "FileSource": "b'\\x03'",
      "ExposureTime": 0.001,
      "FNumber": 8.0,
      "SceneType": "b'\\x01'",
      "ExposureProgram": 1.0,
      "CustomRendered": 0.0,
      "ISOSpeedRatings": 800.0,
      "ExposureMode": 1.0,
      "SensitivityType": 1.0,
      "StandardOutputSensitivity": 800.0,
      "WhiteBalance": 0.0,
      "BodySerialNumber": "71001298",
      "LensSpecification": "(45.0, 100.0, 4.0, 4.0)",
      "LensMake": "FUJIFILM",
      "LensModel": "GF45-100mmF4 R LM OIS WR",
      "LensSerialNumber": "05A00486",
      "SceneCaptureType": 0.0
    },
    "photography": {
      "camera_make": "FUJIFILM",
      "camera_model": "GFX 50S",
      "lens_model": "GF45-100mmF4 R LM OIS WR",
      "aperture": "f/8.0",
      "shutter_speed": "1/1000s",
      "iso": 800.0,
      "focal_length": "100mm",
      "date_original": "2023:04:02 14:17:37",
      "description": "Shoppers at Bangalore's Chikpet area on a Sunday. The modern shopping malls can only look on with envy at footfalls that traditional shopping districts like Chikpet enjoy.",
      "title": "Shoppers at Bangalore's Chikpet area on a Sunday"
    }
  },
  "05.jpg": {
    "filename": "05.jpg",
    "format": "JPEG",
    "size": [
      2272,
      1704
    ],
    "width": 2272,
    "height": 1704,
    "exif": {
      "ResolutionUnit": 2.0,
      "ExifOffset": 346.0,
      "ImageDescription": "Workout sessions at a Talwalkars gym in Vashi, near Mumbai. Mahesh Shantaram for Bloomberg Businessweek.",
      "Make": "NIKON CORPORATION",
      "Model": "NIKON D4S",
      "Software": "Adobe Photoshop Lightroom Classic 15.0.1 (Macintosh)",
      "DateTime": "2025:11:29 17:25:53",
      "XResolution": 240.0,
      "YResolution": 240.0,
      "ExifVersion": "b'0231'",
      "ShutterSpeedValue": 5.906891,
      "ApertureValue": 4.0,
      "DateTimeOriginal": "2017:12:09 19:00:59",
      "DateTimeDigitized": "2017:12:09 19:00:59",
      "ExposureBiasValue": -1.0,
      "MaxApertureValue": 3.0,
      "MeteringMode": 5.0,
      "LightSource": 0.0,
      "Flash": 15.0,
      "FocalLength": 50.0,
      "ColorSpace": 1.0,
      "WhiteBalance": 0.0,
      "DigitalZoomRatio": 1.0,
      "FocalPlaneXResolution": 1368.8888854980469,
      "FocalPlaneYResolution": 1368.8888854980469,
      "OffsetTime": "+05:30",
      "SubsecTimeOriginal": "30",
      "SubsecTimeDigitized": "30",
      "FocalPlaneResolutionUnit": 3.0,
      "SubjectDistanceRange": 0.0,
      "SensingMethod": 2.0,
      "FileSource": "b'\\x03'",
      "ExposureTime": 0.016666666666666666,
      "FNumber": 4.0,
      "SceneType": "b'\\x01'",
      "ExposureProgram": 3.0,
      "CFAPattern": "b'\\x02\\x00\\x02\\x00\\x00\\x01\\x01\\x02'",
      "CustomRendered": 0.0,
      "ISOSpeedRatings": 400.0,
      "ExposureMode": 0.0,
      "SensitivityType": 2.0,
      "BodySerialNumber": "2014595",
      "LensSpecification": "(24.0, 70.0, 2.8, 2.8)",
      "LensModel": "24.0-70.0 mm f/2.8",
      "FocalLengthIn35mmFilm": 50.0,
      "SceneCaptureType": 0.0,
      "GainControl": 1.0,
      "Contrast": 0.0,
      "Saturation": 0.0,
      "Sharpness": 0.0
    },
    "photography": {
      "camera_make": "NIKON CORPORATION",
      "camera_model": "D4S",
      "lens_model": "24.0-70.0 mm f/2.8",
      "aperture": "f/4.0",
      "shutter_speed": "1/60s",
      "iso": 400.0,
      "focal_length": "50mm",
      "date_original": "2017:12:09 19:00:59",
      "description": "Workout sessions at a Talwalkars gym in Vashi, near Mumbai. Mahesh Shantaram for Bloomberg Businessweek.",
      "title": "Workout sessions at a Talwalkars gym in Vashi, near Mumbai"
    }
  },
  "11.jpg": {
    "filename": "11.jpg",
    "format": "JPEG",
    "size": [
      2276,
      1707
    ],
    "width": 2276,
    "height": 1707,
    "exif": {
      "ResolutionUnit": 2.0,
      "ExifOffset": 216.0,
      "Make": "FUJIFILM",
      "Model": "X-T2",
      "Software": "Adobe Photoshop Lightroom Classic 15.0.1 (Macintosh)",
      "DateTime": "2025:11:29 17:25:54",
      "XResolution": 240.0,
      "YResolution": 240.0,
      "ExifVersion": "b'0231'",
      "ShutterSpeedValue": -1.584963,
      "ApertureValue": 8.0,
      "DateTimeOriginal": "2018:09:27 18:46:57",
      "DateTimeDigitized": "2018:09:27 18:46:57",
      "BrightnessValue": -0.54,
      "ExposureBiasValue": 0.0,
      "MaxApertureValue": 3.0,
      "MeteringMode": 5.0,
      "LightSource": 0.0,
      "Flash": 0.0,
      "FocalLength": 34.2,
      "ColorSpace": 1.0,
      "FocalLengthIn35mmFilm": 51.0,
      "FocalPlaneXResolution": 2553.214599609375,
      "FocalPlaneYResolution": 2553.214599609375,
      "OffsetTime": "+05:30",
      "FocalPlaneResolutionUnit": 3.0,
      "Sharpness": 0.0,
      "SubjectDistanceRange": 0.0,
      "SensingMethod": 2.0,
      "FileSource": "b'\\x03'",
      "ExposureTime": 3.0,
      "FNumber": 16.0,
      "SceneType": "b'\\x01'",
      "ExposureProgram": 1.0,
      "CustomRendered": 0.0,
      "ISOSpeedRatings": 200.0,
      "ExposureMode": 1.0,
      "SensitivityType": 1.0,
      "WhiteBalance": 0.0,
      "BodySerialNumber": "73M53215",
      "LensSpecification": "(16.0, 55.0, 2.8, 2.8)",
      "LensMake": "FUJIFILM",
      "LensModel": "XF16-55mmF2.8 R LM WR",
      "LensSerialNumber": "76B30305",
      "SceneCaptureType": 0.0
    },
    "photography": {
      "camera_make": "FUJIFILM",
      "camera_model": "X-T2",
      "lens_model": "XF16-55mmF2.8 R LM WR",
      "aperture": "f/16.0",
      "shutter_speed": "3.0s",
      "iso": 200.0,
      "focal_length": "34mm",
      "date_original": "2018:09:27 18:46:57"
    }
  },
  "10.jpg": {
    "filename": "10.jpg",
    "format": "JPEG",
    "size": [
      2535,
      1870
    ],
    "width": 2535,
    "height": 1870,
    "exif": {
      "ResolutionUnit": 2.0,
      "ExifOffset": 382.0,
      "ImageDescription": "This landscape is unique to the month of December when all houses and establishments are decorated with Christmas lights.",
      "Make": "FUJIFILM",
      "Model": "GFX 50S",
      "Software": "Adobe Photoshop Lightroom Classic 15.0.1 (Macintosh)",
      "DateTime": "2025:11:29 17:25:54",
      "Artist": "MAHESH SHANTARAM",
      "XResolution": 240.0,
      "YResolution": 240.0,
      "ExifVersion": "b'0231'",
      "ShutterSpeedValue": -4.643856,
      "ApertureValue": 6.918863,
      "DateTimeOriginal": "2019:12:08 05:29:16",
      "DateTimeDigitized": "2019:12:08 05:29:16",
      "BrightnessValue": -2.94,
      "ExposureBiasValue": 0.0,
      "MaxApertureValue": 3.0,
      "MeteringMode": 5.0,
      "LightSource": 0.0,
      "Flash": 0.0,
      "FocalLength": 63.0,
      "ColorSpace": 1.0,
      "FocalLengthIn35mmFilm": 50.0,
      "FocalPlaneXResolution": 1876.3636474609375,
      "FocalPlaneYResolution": 1876.3636474609375,
      "OffsetTime": "+05:30",
      "FocalPlaneResolutionUnit": 3.0,
      "Sharpness": 0.0,
      "SubjectDistanceRange": 0.0,
      "SensingMethod": 2.0,
      "FileSource": "b'\\x03'",
      "ExposureTime": 25.0,
      "FNumber": 11.0,
      "SceneType": "b'\\x01'",
      "ExposureProgram": 3.0,
      "CustomRendered": 0.0,
      "ISOSpeedRatings": 100.0,
      "ExposureMode": 0.0,
      "SensitivityType": 1.0,
      "StandardOutputSensitivity": 100.0,
      "WhiteBalance": 0.0,
      "BodySerialNumber": "71001298",
      "LensSpecification": "(63.0, 63.0, 2.8, 2.8)",
      "LensMake": "FUJIFILM",
      "LensModel": "GF63mmF2.8 R WR",
      "LensSerialNumber": "75A01223",
      "SceneCaptureType": 0.0
    },
    "photography": {
      "camera_make": "FUJIFILM",
      "camera_model": "GFX 50S",
      "lens_model": "GF63mmF2.8 R WR",
      "aperture": "f/11.0",
      "shutter_speed": "25.0s",
      "iso": 100.0,
      "focal_length": "63mm",
      "date_original": "2019:12:08 05:29:16",
      "artist": "MAHESH SHANTARAM",
      "description": "This landscape is unique to the month of December when all houses and establishments are decorated with Christmas lights."
    }
  },
  "04.jpg": {
    "filename": "04.jpg",
    "format": "JPEG",
    "size": [
      2276,
      1707
    ],
    "width": 2276,
    "height": 1707,
    "exif": {
      "GPSInfo": "{0: b'\\x02\\x02\\x00\\x00', 1: 'N', 2: (12.0, 44.9559, 0.0), 3: 'E', 4: (77.0, 44.07936, 0.0)}",
      "ResolutionUnit": 2.0,
      "ExifOffset": 398.0,
      "ImageDescription": "Contract workers perform stretching exercises as soon as they arrive for their shift. Amazon's new fulfillment centre in Attibele, Karnataka near Bangalore.",
      "Make": "FUJIFILM",
      "Model": "X-T2",
      "Software": "Adobe Photoshop Lightroom Classic 15.0.1 (Macintosh)",
      "DateTime": "2025:11:29 17:25:53",
      "XResolution": 240.0,
      "YResolution": 240.0,
      "ExifVersion": "b'0231'",
      "ShutterSpeedValue": 6.965784,
      "ApertureValue": 2.970854,
      "DateTimeOriginal": "2018:09:18 18:35:56",
      "DateTimeDigitized": "2018:09:18 18:35:56",
      "BrightnessValue": 1.08,
      "ExposureBiasValue": 0.0,
      "MaxApertureValue": 3.0,
      "MeteringMode": 5.0,
      "LightSource": 0.0,
      "Flash": 1.0,
      "FocalLength": 17.6,
      "ColorSpace": 1.0,
      "FocalLengthIn35mmFilm": 26.0,
      "FocalPlaneXResolution": 2553.214599609375,
      "FocalPlaneYResolution": 2553.214599609375,
      "OffsetTime": "+05:30",
      "FocalPlaneResolutionUnit": 3.0,
      "Sharpness": 0.0,
      "SubjectDistanceRange": 0.0,
      "SensingMethod": 2.0,
      "FileSource": "b'\\x03'",
      "ExposureTime": 0.008,
      "FNumber": 2.8,
      "SceneType": "b'\\x01'",
      "ExposureProgram": 1.0,
      "CustomRendered": 0.0,
      "ISOSpeedRatings": 1600.0,
      "ExposureMode": 1.0,
      "SensitivityType": 1.0,
      "WhiteBalance": 0.0,
      "BodySerialNumber": "73M53215",
      "LensSpecification": "(16.0, 55.0, 2.8, 2.8)",
      "LensMake": "FUJIFILM",
      "LensModel": "XF16-55mmF2.8 R LM WR",
      "LensSerialNumber": "76B30305",
      "SceneCaptureType": 0.0
    },
    "photography": {
      "camera_make": "FUJIFILM",
      "camera_model": "X-T2",
      "lens_model": "XF16-55mmF2.8 R LM WR",
      "aperture": "f/2.8",
      "shutter_speed": "1/125s",
      "iso": 1600.0,
      "focal_length": "18mm",
      "date_original": "2018:09:18 18:35:56",
      "description": "Contract workers perform stretching exercises as soon as they arrive for their shift. Amazon's new fulfillment centre in Attibele, Karnataka near Bangalore.",
      "title": "Contract workers perform stretching exercises as soon as they arrive for their shift"
    }
  },
  "21.jpg": {
    "filename": "21.jpg",
    "format": "JPEG",
    "size": [
      2560,
      1920
    ],
    "width": 2560,
    "height": 1920,
    "exif": {
      "ResolutionUnit": 2.0,
      "ExifOffset": 362.0,
      "ImageDescription": "In an extreme display oif devotion, Shubam Garg has travelled 130 Km from Lucknow to Ayodhya by prostrating every step of the way.",
      "Make": "FUJIFILM",
      "Model": "GFX 50S",
      "Software": "Adobe Photoshop Lightroom Classic 15.0.1 (Macintosh)",
      "DateTime": "2025:11:29 17:25:56",
      "XResolution": 240.0,
      "YResolution": 240.0,
      "ExifVersion": "b'0231'",
      "ShutterSpeedValue": 4.906891,
      "ApertureValue": 4.970854,
      "DateTimeOriginal": "2024:01:17 17:32:28",
      "DateTimeDigitized": "2024:01:17 17:32:28",
      "BrightnessValue": 1.64,
      "ExposureBiasValue": 0.0,
      "MaxApertureValue": 4.0,
      "MeteringMode": 5.0,
      "LightSource": 0.0,
      "Flash": 1.0,
      "FocalLength": 45.0,
      "ColorSpace": 1.0,
      "FocalLengthIn35mmFilm": 36.0,
      "FocalPlaneXResolution": 1876.3636474609375,
      "FocalPlaneYResolution": 1876.3636474609375,
      "OffsetTime": "+05:30",
      "FocalPlaneResolutionUnit": 3.0,
      "Sharpness": 0.0,
      "SubjectDistanceRange": 0.0,
      "SensingMethod": 2.0,
      "FileSource": "b'\\x03'",
      "ExposureTime": 0.03333333333333333,
      "FNumber": 5.6,
      "SceneType": "b'\\x01'",
      "ExposureProgram": 3.0,
      "CustomRendered": 0.0,
      "ISOSpeedRatings": 800.0,
      "ExposureMode": 0.0,
      "SensitivityType": 1.0,
      "StandardOutputSensitivity": 800.0,
      "WhiteBalance": 0.0,
      "BodySerialNumber": "71001298",
      "LensSpecification": "(45.0, 100.0, 4.0, 4.0)",
      "LensMake": "FUJIFILM",
      "LensModel": "GF45-100mmF4 R LM OIS WR",
      "LensSerialNumber": "05A00486",
      "SceneCaptureType": 0.0
    },
    "photography": {
      "camera_make": "FUJIFILM",
      "camera_model": "GFX 50S",
      "lens_model": "GF45-100mmF4 R LM OIS WR",
      "aperture": "f/5.6",
      "shutter_speed": "1/30s",
      "iso": 800.0,
      "focal_length": "45mm",
      "date_original": "2024:01:17 17:32:28",
      "description": "In an extreme display oif devotion, Shubam Garg has travelled 130 Km from Lucknow to Ayodhya by prostrating every step of the way."
    }
  },
  "09.jpg": {
    "filename": "09.jpg",
    "format": "JPEG",
    "size": [
      2560,
      1920
    ],
    "width": 2560,
    "height": 1920,
    "exif": {
      "ResolutionUnit": 2.0,
      "ExifOffset": 652.0,
      "ImageDescription": "I was at a fair at Solidarity Park when I saw Ketsei arrive on his motorcycle. I mistook his bike to be a Harley-Davidson but it turned out to be a heavily modified Bajaj Avenger with a Harley logo stuck on to it. Ketsei is a dealer of motorcycle spares and accessories. He belongs to Angami tribe and lives in Kohima village, the original owners of the land on which the city stands today.",
      "Make": "FUJIFILM",
      "Model": "GFX 50S",
      "Software": "Adobe Photoshop Lightroom Classic 15.0.1 (Macintosh)",
      "DateTime": "2025:11:29 17:25:54",
      "Artist": "MAHESH SHANTARAM",
      "XResolution": 240.0,
      "YResolution": 240.0,
      "ExifVersion": "b'0231'",
      "ShutterSpeedValue": 1.0,
      "ApertureValue": 2.970854,
      "DateTimeOriginal": "2019:12:06 16:55:07",
      "DateTimeDigitized": "2019:12:06 16:55:07",
      "BrightnessValue": -0.4,
      "ExposureBiasValue": 0.0,
      "MaxApertureValue": 3.0,
      "MeteringMode": 5.0,
      "LightSource": 0.0,
      "Flash": 0.0,
      "FocalLength": 63.0,
      "ColorSpace": 1.0,
      "FocalLengthIn35mmFilm": 50.0,
      "FocalPlaneXResolution": 1876.3636474609375,
      "FocalPlaneYResolution": 1876.3636474609375,
      "OffsetTime": "+05:30",
      "FocalPlaneResolutionUnit": 3.0,
      "Sharpness": 0.0,
      "SubjectDistanceRange": 0.0,
      "SensingMethod": 2.0,
      "FileSource": "b'\\x03'",
      "ExposureTime": 0.5,
      "FNumber": 2.8,
      "SceneType": "b'\\x01'",
      "ExposureProgram": 3.0,
      "CustomRendered": 0.0,
      "ISOSpeedRatings": 100.0,
      "ExposureMode": 0.0,
      "SensitivityType": 1.0,
      "StandardOutputSensitivity": 100.0,
      "WhiteBalance": 0.0,
      "BodySerialNumber": "71001298",
      "LensSpecification": "(63.0, 63.0, 2.8, 2.8)",
      "LensMake": "FUJIFILM",
      "LensModel": "GF63mmF2.8 R WR",
      "LensSerialNumber": "75A01223",
      "SceneCaptureType": 0.0
    },
    "photography": {
      "camera_make": "FUJIFILM",
      "camera_model": "GFX 50S",
      "lens_model": "GF63mmF2.8 R WR",
      "aperture": "f/2.8",
      "shutter_speed": "1/2s",
      "iso": 100.0,
      "focal_length": "63mm",
      "date_original": "2019:12:06 16:55:07",
      "artist": "MAHESH SHANTARAM",
      "description": "I was at a fair at Solidarity Park when I saw Ketsei arrive on his motorcycle. I mistook his bike to be a Harley-Davidson but it turned out to be a heavily modified Bajaj Avenger with a Harley logo stuck on to it. Ketsei is a dealer of motorcycle spares and accessories. He belongs to Angami tribe and lives in Kohima village, the original owners of the land on which the city stands today.",
      "title": "I was at a fair at Solidarity Park when I saw Ketsei arrive on his motorcycle"
    }
  },
  "08.jpg": {
    "filename": "08.jpg",
    "format": "JPEG",
    "size": [
      2276,
      1707
    ],
    "width": 2276,
    "height": 1707,
    "exif": {
      "ResolutionUnit": 2.0,
      "ExifOffset": 714.0,
      "ImageDescription": "Naga Chili Eating Competition - While this annual competition art Hornbill Festival attracts many curious competitors and provides much entertainment, the Nagas take their chilli very seriously. In the end, the grand prize winner was a Naga man who came all the way from Tuensang. Immediately after their round, competitors are whisked away backstage where a medical team awaits them. They are given milk and cream to mitigate the burning sensation and their blood pressure is tested.",
      "Make": "FUJIFILM",
      "Model": "X-T2",
      "Software": "Adobe Photoshop Lightroom Classic 15.0.1 (Macintosh)",
      "DateTime": "2025:11:29 17:25:54",
      "XResolution": 240.0,
      "YResolution": 240.0,
      "ExifVersion": "b'0231'",
      "ShutterSpeedValue": 7.321928,
      "ApertureValue": 4.0,
      "DateTimeOriginal": "2019:12:07 17:04:58",
      "DateTimeDigitized": "2019:12:07 17:04:58",
      "BrightnessValue": 5.3,
      "ExposureBiasValue": 0.0,
      "MaxApertureValue": 3.0,
      "MeteringMode": 2.0,
      "LightSource": 0.0,
      "Flash": 1.0,
      "FocalLength": 22.7,
      "ColorSpace": 1.0,
      "FocalLengthIn35mmFilm": 34.0,
      "FocalPlaneXResolution": 2553.214599609375,
      "FocalPlaneYResolution": 2553.214599609375,
      "OffsetTime": "+05:30",
      "FocalPlaneResolutionUnit": 3.0,
      "Sharpness": 0.0,
      "SubjectDistanceRange": 0.0,
      "SensingMethod": 2.0,
      "FileSource": "b'\\x03'",
      "ExposureTime": 0.00625,
      "FNumber": 4.0,
      "SceneType": "b'\\x01'",
      "ExposureProgram": 3.0,
      "CustomRendered": 0.0,
      "ISOSpeedRatings": 200.0,
      "ExposureMode": 0.0,
      "SensitivityType": 1.0,
      "WhiteBalance": 0.0,
      "BodySerialNumber": "73M53215",
      "LensSpecification": "(16.0, 55.0, 2.8, 2.8)",
      "LensMake": "FUJIFILM",
      "LensModel": "XF16-55mmF2.8 R LM WR",
      "LensSerialNumber": "76B30305",
      "SceneCaptureType": 0.0
    },
    "photography": {
      "camera_make": "FUJIFILM",
      "camera_model": "X-T2",
      "lens_model": "XF16-55mmF2.8 R LM WR",
      "aperture": "f/4.0",
      "shutter_speed": "1/160s",
      "iso": 200.0,
      "focal_length": "23mm",
      "date_original": "2019:12:07 17:04:58",
      "description": "Naga Chili Eating Competition - While this annual competition art Hornbill Festival attracts many curious competitors and provides much entertainment, the Nagas take their chilli very seriously. In the end, the grand prize winner was a Naga man who came all the way from Tuensang. Immediately after their round, competitors are whisked away backstage where a medical team awaits them. They are given milk and cream to mitigate the burning sensation and their blood pressure is tested."
    }
  },
  "20.jpg": {
    "filename": "20.jpg",
    "format": "JPEG",
    "size": [
      1765,
      2353
    ],
    "width": 1765,
    "height": 2353,
    "exif": {
      "GPSInfo": "{0: b'\\x02\\x02\\x00\\x00', 1: 'N', 2: (12.0, 59.57652, 0.0), 3: 'E', 4: (77.0, 45.43782, 0.0)}",
      "ResolutionUnit": 2.0,
      "ExifOffset": 420.0,
      "ImageDescription": "Fans of Narendra Modi and BJP party workers queue up to catch a glimpse of the prime minister who was in Bangalore to inaugurate the as-yet-incomplete metro line in Whitefield.",
      "Make": "FUJIFILM",
      "Model": "GFX 50S",
      "Software": "Adobe Photoshop Lightroom Classic 15.0.1 (Macintosh)",
      "DateTime": "2025:11:29 17:25:56",
      "XResolution": 240.0,
      "YResolution": 240.0,
      "ExifVersion": "b'0231'",
      "ShutterSpeedValue": 9.965784,
      "ApertureValue": 4.0,
      "DateTimeOriginal": "2023:03:25 13:06:18",
      "DateTimeDigitized": "2023:03:25 13:06:18",
      "BrightnessValue": 7.22,
      "ExposureBiasValue": 0.0,
      "MaxApertureValue": 4.0,
      "MeteringMode": 5.0,
      "LightSource": 0.0,
      "Flash": 1.0,
      "FocalLength": 45.0,
      "ColorSpace": 1.0,
      "FocalLengthIn35mmFilm": 36.0,
      "FocalPlaneXResolution": 1876.3636474609375,
      "FocalPlaneYResolution": 1876.3636474609375,
      "OffsetTime": "+05:30",
      "FocalPlaneResolutionUnit": 3.0,
      "Sharpness": 0.0,
      "SubjectDistanceRange": 0.0,
      "SensingMethod": 2.0,
      "FileSource": "b'\\x03'",
      "ExposureTime": 0.001,
      "FNumber": 4.0,
      "SceneType": "b'\\x01'",
      "ExposureProgram": 1.0,
      "CustomRendered": 0.0,
      "ISOSpeedRatings": 400.0,
      "ExposureMode": 1.0,
      "SensitivityType": 1.0,
      "StandardOutputSensitivity": 400.0,
      "WhiteBalance": 0.0,
      "BodySerialNumber": "71001298",
      "LensSpecification": "(45.0, 100.0, 4.0, 4.0)",
      "LensMake": "FUJIFILM",
      "LensModel": "GF45-100mmF4 R LM OIS WR",
      "LensSerialNumber": "05A00486",
      "SceneCaptureType": 0.0
    },
    "photography": {
      "camera_make": "FUJIFILM",
      "camera_model": "GFX 50S",
      "lens_model": "GF45-100mmF4 R LM OIS WR",
      "aperture": "f/4.0",
      "shutter_speed": "1/1000s",
      "iso": 400.0,
      "focal_length": "45mm",
      "date_original": "2023:03:25 13:06:18",
      "description": "Fans of Narendra Modi and BJP party workers queue up to catch a glimpse of the prime minister who was in Bangalore to inaugurate the as-yet-incomplete metro line in Whitefield."
    }
  },
  "22.jpg": {
    "filename": "22.jpg",
    "format": "JPEG",
    "size": [
      2276,
      1707
    ],
    "width": 2276,
    "height": 1707,
    "exif": {
      "ResolutionUnit": 2.0,
      "ExifOffset": 668.0,
      "ImageDescription": "Ayodhya's new airport (about two weeks old) features motifs from the Indian epic Ramayana based on the life of Ram. In the background is a depiction of the scene when Ram returns with Sita to Ayodhya after a 14-year exile. In the foreground, a more mundane reality plays out. A couple is worried about their missing baggage. Others are struggling to fit the giant mural into their selfie or making calls to check on their airport pick-up.",
      "Make": "FUJIFILM",
      "Model": "X-T5",
      "Software": "Adobe Photoshop Lightroom Classic 15.0.1 (Macintosh)",
      "DateTime": "2025:11:29 17:25:56",
      "XResolution": 240.0,
      "YResolution": 240.0,
      "ExifVersion": "b'0232'",
      "ShutterSpeedValue": 7.409391,
      "ApertureValue": 4.0,
      "DateTimeOriginal": "2024:01:17 11:43:31",
      "DateTimeDigitized": "2024:01:17 14:13:31",
      "BrightnessValue": 2.81,
      "ExposureBiasValue": -0.67,
      "MaxApertureValue": 1.0,
      "MeteringMode": 5.0,
      "LightSource": 0.0,
      "Flash": 0.0,
      "FocalLength": 23.0,
      "CameraElevationAngle": 5.3,
      "ColorSpace": 1.0,
      "FocalPlaneXResolution": 3303.855743408203,
      "FocalPlaneYResolution": 3303.855743408203,
      "OffsetTime": "+05:30",
      "OffsetTimeOriginal": "+05:30",
      "OffsetTimeDigitized": "+05:30",
      "FocalPlaneResolutionUnit": 3.0,
      "SubjectDistanceRange": 0.0,
      "SensingMethod": 2.0,
      "FileSource": "b'\\x03'",
      "ExposureTime": 0.0058823529411764705,
      "FNumber": 4.0,
      "SceneType": "b'\\x01'",
      "ExposureProgram": 3.0,
      "CustomRendered": 0.0,
      "ISOSpeedRatings": 800.0,
      "ExposureMode": 0.0,
      "SensitivityType": 1.0,
      "WhiteBalance": 0.0,
      "BodySerialNumber": "3BA08208",
      "LensSpecification": "(23.0, 23.0, 1.4, 1.4)",
      "LensMake": "FUJIFILM",
      "LensModel": "XF23mmF1.4 R LM WR",
      "LensSerialNumber": "2CA02147",
      "FocalLengthIn35mmFilm": 35.0,
      "SceneCaptureType": 0.0,
      "Sharpness": 0.0
    },
    "photography": {
      "camera_make": "FUJIFILM",
      "camera_model": "X-T5",
      "lens_model": "XF23mmF1.4 R LM WR",
      "aperture": "f/4.0",
      "shutter_speed": "1/170s",
      "iso": 800.0,
      "focal_length": "23mm",
      "date_original": "2024:01:17 11:43:31",
      "description": "Ayodhya's new airport (about two weeks old) features motifs from the Indian epic Ramayana based on the life of Ram. In the background is a depiction of the scene when Ram returns with Sita to Ayodhya after a 14-year exile. In the foreground, a more mundane reality plays out. A couple is worried about their missing baggage. Others are struggling to fit the giant mural into their selfie or making calls to check on their airport pick-up."
    }
  },
  "23.jpg": {
    "filename": "23.jpg",
    "format": "JPEG",
    "size": [
      2560,
      1920
    ],
    "width": 2560,
    "height": 1920,
    "exif": {
      "ResolutionUnit": 2.0,
      "ExifOffset": 318.0,
      "ImageDescription": "Ayodhya Dham Junction railway station and construction of a modern terminal extension.",
      "Make": "FUJIFILM",
      "Model": "GFX 50S",
      "Software": "Adobe Photoshop Lightroom Classic 15.0.1 (Macintosh)",
      "DateTime": "2025:11:29 17:25:56",
      "XResolution": 240.0,
      "YResolution": 240.0,
      "ExifVersion": "b'0231'",
      "ShutterSpeedValue": 5.906891,
      "ApertureValue": 4.0,
      "DateTimeOriginal": "2024:01:19 17:39:35",
      "DateTimeDigitized": "2024:01:19 17:39:35",
      "BrightnessValue": 1.34,
      "ExposureBiasValue": 0.0,
      "MaxApertureValue": 4.0,
      "MeteringMode": 5.0,
      "LightSource": 0.0,
      "Flash": 0.0,
      "FocalLength": 45.0,
      "ColorSpace": 1.0,
      "FocalLengthIn35mmFilm": 36.0,
      "FocalPlaneXResolution": 1876.3636474609375,
      "FocalPlaneYResolution": 1876.3636474609375,
      "OffsetTime": "+05:30",
      "FocalPlaneResolutionUnit": 3.0,
      "Sharpness": 0.0,
      "SubjectDistanceRange": 0.0,
      "SensingMethod": 2.0,
      "FileSource": "b'\\x03'",
      "ExposureTime": 0.016666666666666666,
      "FNumber": 4.0,
      "SceneType": "b'\\x01'",
      "ExposureProgram": 1.0,
      "CustomRendered": 0.0,
      "ISOSpeedRatings": 1600.0,
      "ExposureMode": 1.0,
      "SensitivityType": 1.0,
      "StandardOutputSensitivity": 1600.0,
      "WhiteBalance": 0.0,
      "BodySerialNumber": "71001298",
      "LensSpecification": "(45.0, 100.0, 4.0, 4.0)",
      "LensMake": "FUJIFILM",
      "LensModel": "GF45-100mmF4 R LM OIS WR",
      "LensSerialNumber": "05A00486",
      "SceneCaptureType": 0.0
    },
    "photography": {
      "camera_make": "FUJIFILM",
      "camera_model": "GFX 50S",
      "lens_model": "GF45-100mmF4 R LM OIS WR",
      "aperture": "f/4.0",
      "shutter_speed": "1/60s",
      "iso": 1600.0,
      "focal_length": "45mm",
      "date_original": "2024:01:19 17:39:35",
      "description": "Ayodhya Dham Junction railway station and construction of a modern terminal extension."
    }
  },
  "18.jpg": {
    "filename": "18.jpg",
    "format": "JPEG",
    "size": [
      2320,
      1740
    ],
    "width": 2320,
    "height": 1740,
    "exif": {
      "GPSInfo": "{0: b'\\x02\\x02\\x00\\x00', 1: 'N', 2: (12.0, 59.15712, 0.0), 3: 'E', 4: (77.0, 35.48676, 0.0)}",
      "ResolutionUnit": 2.0,
      "ExifOffset": 416.0,
      "ImageDescription": "Mohammed Zubair, co-founder of AltNews, photographed at a public garden in Bangalore where retired military and defense equipment are kept for public display and admiration.",
      "Make": "FUJIFILM",
      "Model": "GFX 50S",
      "Software": "Adobe Photoshop Lightroom Classic 15.0.1 (Macintosh)",
      "DateTime": "2025:11:29 17:25:56",
      "XResolution": 240.0,
      "YResolution": 240.0,
      "ExifVersion": "b'0231'",
      "ShutterSpeedValue": 7.965784,
      "ApertureValue": 4.0,
      "DateTimeOriginal": "2023:03:23 17:39:34",
      "DateTimeDigitized": "2023:03:23 17:39:34",
      "BrightnessValue": 3.9,
      "ExposureBiasValue": 0.0,
      "MaxApertureValue": 4.0,
      "MeteringMode": 5.0,
      "LightSource": 0.0,
      "Flash": 1.0,
      "FocalLength": 59.8,
      "ColorSpace": 1.0,
      "FocalLengthIn35mmFilm": 47.0,
      "FocalPlaneXResolution": 1876.3636474609375,
      "FocalPlaneYResolution": 1876.3636474609375,
      "OffsetTime": "+05:30",
      "FocalPlaneResolutionUnit": 3.0,
      "Sharpness": 0.0,
      "SubjectDistanceRange": 0.0,
      "SensingMethod": 2.0,
      "FileSource": "b'\\x03'",
      "ExposureTime": 0.004,
      "FNumber": 4.0,
      "SceneType": "b'\\x01'",
      "ExposureProgram": 1.0,
      "CustomRendered": 0.0,
      "ISOSpeedRatings": 100.0,
      "ExposureMode": 1.0,
      "SensitivityType": 1.0,
      "StandardOutputSensitivity": 100.0,
      "WhiteBalance": 0.0,
      "BodySerialNumber": "71001298",
      "LensSpecification": "(45.0, 100.0, 4.0, 4.0)",
      "LensMake": "FUJIFILM",
      "LensModel": "GF45-100mmF4 R LM OIS WR",
      "LensSerialNumber": "05A00486",
      "SceneCaptureType": 0.0
    },
    "photography": {
      "camera_make": "FUJIFILM",
      "camera_model": "GFX 50S",
      "lens_model": "GF45-100mmF4 R LM OIS WR",
      "aperture": "f/4.0",
      "shutter_speed": "1/250s",
      "iso": 100.0,
      "focal_length": "60mm",
      "date_original": "2023:03:23 17:39:34",
      "description": "Mohammed Zubair, co-founder of AltNews, photographed at a public garden in Bangalore where retired military and defense equipment are kept for public display and admiration."
    }
  },
  "24.jpg": {
    "filename": "24.jpg",
    "format": "JPEG",
    "size": [
      2276,
      1707
    ],
    "width": 2276,
    "height": 1707,
    "exif": {
      "ResolutionUnit": 2.0,
      "ExifOffset": 216.0,
      "Make": "FUJIFILM",
      "Model": "X-T5",
      "Software": "Adobe Photoshop Lightroom Classic 15.0.1 (Macintosh)",
      "DateTime": "2025:11:29 17:25:56",
      "XResolution": 240.0,
      "YResolution": 240.0,
      "ExifVersion": "b'0232'",
      "ShutterSpeedValue": 6.965784,
      "ApertureValue": 4.0,
      "DateTimeOriginal": "2023:08:26 18:31:03",
      "DateTimeDigitized": "2023:08:26 18:31:03",
      "BrightnessValue": 2.73,
      "ExposureBiasValue": 0.0,
      "MaxApertureValue": 1.0,
      "MeteringMode": 5.0,
      "LightSource": 0.0,
      "Flash": 1.0,
      "FocalLength": 23.0,
      "CameraElevationAngle": 4.1,
      "ColorSpace": 1.0,
      "FocalPlaneXResolution": 3303.855743408203,
      "FocalPlaneYResolution": 3303.855743408203,
      "OffsetTime": "+05:30",
      "OffsetTimeOriginal": "+05:30",
      "OffsetTimeDigitized": "+05:30",
      "FocalPlaneResolutionUnit": 3.0,
      "SubjectDistanceRange": 0.0,
      "SensingMethod": 2.0,
      "FileSource": "b'\\x03'",
      "ExposureTime": 0.008,
      "FNumber": 4.0,
      "SceneType": "b'\\x01'",
      "ExposureProgram": 3.0,
      "CustomRendered": 0.0,
      "ISOSpeedRatings": 1600.0,
      "ExposureMode": 0.0,
      "SensitivityType": 1.0,
      "WhiteBalance": 0.0,
      "BodySerialNumber": "3BA08208",
      "LensSpecification": "(23.0, 23.0, 1.4, 1.4)",
      "LensMake": "FUJIFILM",
      "LensModel": "XF23mmF1.4 R LM WR",
      "LensSerialNumber": "2CA02147",
      "FocalLengthIn35mmFilm": 35.0,
      "SceneCaptureType": 0.0,
      "Sharpness": 0.0
    },
    "photography": {
      "camera_make": "FUJIFILM",
      "camera_model": "X-T5",
      "lens_model": "XF23mmF1.4 R LM WR",
      "aperture": "f/4.0",
      "shutter_speed": "1/125s",
      "iso": 1600.0,
      "focal_length": "23mm",
      "date_original": "2023:08:26 18:31:03"
    }
  },
  "25.jpg": {
    "filename": "25.jpg",
    "format": "JPEG",
    "size": [
      2560,
      1920
    ],
    "width": 2560,
    "height": 1920,
    "exif": {
      "ResolutionUnit": 2.0,
      "ExifOffset": 290.0,
      "Make": "OLYMPUS IMAGING CORP.",
      "Model": "E-300",
      "Software": "Adobe Photoshop Lightroom Classic 15.0.1 (Macintosh)",
      "DateTime": "2025:11:29 17:28:58",
      "Artist": "Mahesh Shantaram",
      "Copyright": "© Mahesh Shantaram",
      "XResolution": 240.0,
      "YResolution": 240.0,
      "ExifVersion": "b'0231'",
      "ShutterSpeedValue": 6.965784,
      "ApertureValue": 3.61471,
      "DateTimeOriginal": "2007:06:23 06:23:19",
      "DateTimeDigitized": "2007:06:23 06:23:19",
      "ExposureBiasValue": 0.0,
      "MaxApertureValue": 2.97265625,
      "MeteringMode": 5.0,
      "LightSource": 10.0,
      "Flash": 16.0,
      "FocalLength": 46.0,
      "ColorSpace": 1.0,
      "WhiteBalance": 1.0,
      "DigitalZoomRatio": 1.0,
      "FocalLengthIn35mmFilm": 92.0,
      "SceneCaptureType": 0.0,
      "OffsetTime": "+05:30",
      "OffsetTimeOriginal": "+06:00",
      "OffsetTimeDigitized": "+06:00",
      "Sharpness": 0.0,
      "FileSource": "b'\\x03'",
      "ExposureTime": 0.008,
      "FNumber": 3.5,
      "ExposureProgram": 2.0,
      "CFAPattern": "b'\\x02\\x00\\x02\\x00\\x00\\x01\\x01\\x02'",
      "CustomRendered": 0.0,
      "ISOSpeedRatings": 400.0,
      "ExposureMode": 0.0,
      "BodySerialNumber": "623502042",
      "LensSpecification": "(14.0, 54.0, 2.8, 3.5)",
      "LensModel": "14.0-54.0 mm f/2.8-3.5",
      "LensSerialNumber": "050307104",
      "GainControl": 2.0,
      "Contrast": 2.0,
      "Saturation": 1.0
    },
    "photography": {
      "camera_make": "OLYMPUS IMAGING CORP.",
      "camera_model": "E-300",
      "lens_model": "14.0-54.0 mm f/2.8-3.5",
      "aperture": "f/3.5",
      "shutter_speed": "1/125s",
      "iso": 400.0,
      "focal_length": "46mm",
      "date_original": "2007:06:23 06:23:19",
      "artist": "Mahesh Shantaram",
      "copyright": "© Mahesh Shantaram"
    }
  },
  "19.jpg": {
    "filename": "19.jpg",
    "format": "JPEG",
    "size": [
      2449,
      1633
    ],
    "width": 2449,
    "height": 1633,
    "exif": {
      "ResolutionUnit": 2.0,
      "ExifOffset": 216.0,
      "Make": "FUJIFILM",
      "Model": "X-T5",
      "Software": "Adobe Photoshop Lightroom Classic 15.0.1 (Macintosh)",
      "DateTime": "2025:11:29 17:25:56",
      "XResolution": 240.0,
      "YResolution": 240.0,
      "ExifVersion": "b'0232'",
      "ShutterSpeedValue": 10.965784,
      "ApertureValue": 2.970854,
      "DateTimeOriginal": "2023:08:15 16:07:32",
      "DateTimeDigitized": "2023:08:15 16:07:32",
      "BrightnessValue": 4.33,
      "ExposureBiasValue": 0.0,
      "MaxApertureValue": 1.0,
      "MeteringMode": 5.0,
      "LightSource": 0.0,
      "Flash": 1.0,
      "FocalLength": 23.0,
      "CameraElevationAngle": -4.5,
      "ColorSpace": 1.0,
      "FocalPlaneXResolution": 3303.855743408203,
      "FocalPlaneYResolution": 3303.855743408203,
      "OffsetTime": "+05:30",
      "OffsetTimeOriginal": "+05:30",
      "OffsetTimeDigitized": "+05:30",
      "FocalPlaneResolutionUnit": 3.0,
      "SubjectDistanceRange": 0.0,
      "SensingMethod": 2.0,
      "FileSource": "b'\\x03'",
      "ExposureTime": 0.0005,
      "FNumber": 2.8,
      "SceneType": "b'\\x01'",
      "ExposureProgram": 1.0,
      "CustomRendered": 0.0,
      "ISOSpeedRatings": 800.0,
      "ExposureMode": 1.0,
      "SensitivityType": 1.0,
      "WhiteBalance": 0.0,
      "BodySerialNumber": "3BA08208",
      "LensSpecification": "(23.0, 23.0, 1.4, 1.4)",
      "LensMake": "FUJIFILM",
      "LensModel": "XF23mmF1.4 R LM WR",
      "LensSerialNumber": "2CA02147",
      "FocalLengthIn35mmFilm": 35.0,
      "SceneCaptureType": 0.0,
      "Sharpness": 0.0
    },
    "photography": {
      "camera_make": "FUJIFILM",
      "camera_model": "X-T5",
      "lens_model": "XF23mmF1.4 R LM WR",
      "aperture": "f/2.8",
      "shutter_speed": "1/2000s",
      "iso": 800.0,
      "focal_length": "23mm",
      "date_original": "2023:08:15 16:07:32"
    }
  }
}